wolfsoftware/data_converter/__init__.py
wolfsoftware/data_converter/dataconverter.py
wolfsoftware/data_converter/exceptions.py
wolfsoftware.data_converter-0.1.1.dist-info/LICENSE.md
wolfsoftware.data_converter-0.1.1.dist-info/METADATA
wolfsoftware.data_converter-0.1.1.dist-info/WHEEL
wolfsoftware.data_converter-0.1.1.dist-info/top_level.txt
wolfsoftware.data_converter-0.1.1.dist-info/RECORD
